eda_profiler/__init__.py
eda_profiler/profiler.py
eda_profiler-0.1.2.dist-info/licenses/LICENSE
eda_profiler-0.1.2.dist-info/METADATA
eda_profiler-0.1.2.dist-info/WHEEL
eda_profiler-0.1.2.dist-info/top_level.txt
eda_profiler-0.1.2.dist-info/RECORD
