Metadata-Version: 2.4
Name: eda_profiler
Version: 0.1.2
Summary: A lightweight package for detailed Exploratory Data Analysis on pandas DataFrames.
Author-email: Dinesh Kumar <dineshkumarjangid@gmail.com>
Project-URL: Homepage, https://github.com/dineshjangid/eda_profiler
Project-URL: Issues, https://github.com/dineshjangid/eda_profiler/issues
Classifier: Programming Language :: Python :: 3
Classifier: License :: OSI Approved :: MIT License
Classifier: Operating System :: OS Independent
Classifier: Intended Audience :: Developers
Classifier: Intended Audience :: Science/Research
Classifier: Topic :: Scientific/Engineering :: Information Analysis
Requires-Python: >=3.8
License-File: LICENSE
Requires-Dist: pandas>=1.0.0
Requires-Dist: numpy>=1.18.0
Dynamic: license-file
